Experiment notebooks/__init__.py
Experiment notebooks/_processing_funcs.py
Experiment notebooks/clustering_program_utils.py
lgp/__init__.py
lgp/_evolve.py
lgp/_genetic_operations.py
lgp/_instruction.py
lgp/_population.py
lgp/_program.py
lgp/lgp_classifier.py
lgp/tests/__init__.py
lgp/tests/test_lgp.py
linear_genetic_programming/__init__.py
linear_genetic_programming/_evolve.py
linear_genetic_programming/_genetic_operations.py
linear_genetic_programming/_instruction.py
linear_genetic_programming/_population.py
linear_genetic_programming/_program.py
linear_genetic_programming/lgp_classifier.py
linear_genetic_programming/tests/__init__.py
linear_genetic_programming/tests/test_lgp.py
lgp-0.0.6.dist-info/LICENSE
lgp-0.0.6.dist-info/METADATA
lgp-0.0.6.dist-info/WHEEL
lgp-0.0.6.dist-info/top_level.txt
lgp-0.0.6.dist-info/RECORD
